pypackagebuilder/__init__.py
pypackagebuilder/__main__.py
pypackagebuilder-0.3.0.dist-info/LICENSE
pypackagebuilder-0.3.0.dist-info/METADATA
pypackagebuilder-0.3.0.dist-info/WHEEL
pypackagebuilder-0.3.0.dist-info/top_level.txt
pypackagebuilder-0.3.0.dist-info/zip-safe
pypackagebuilder-0.3.0.dist-info/RECORD
